mxfp/__init__.py
mxfp/mxfp.py
mxfp-1.1.3.dist-info/LICENSE
mxfp-1.1.3.dist-info/METADATA
mxfp-1.1.3.dist-info/WHEEL
mxfp-1.1.3.dist-info/top_level.txt
mxfp-1.1.3.dist-info/RECORD
