Metadata-Version: 2.1
Name: mxfp
Version: 1.1.3
Summary: MXFP
Author: Markus Orsi
Author-email: <markus.orsi@unibe.ch>
Keywords: cheminformatics,mxfp,fingerprint
Classifier: Development Status :: 3 - Alpha
Classifier: Intended Audience :: Education
Classifier: Programming Language :: Python :: 3
Classifier: Operating System :: MacOS :: MacOS X
Classifier: Operating System :: Microsoft :: Windows
License-File: LICENSE
